Metadata-Version: 2.1
Name: jackknife
Version: 0.1.0
Summary: Jackknife resampling, parameter estimation and stability test
Home-page: http://github.com/kmedian/jackknife
Author: Ulf Hamster
Author-email: 554c46@gmail.com
License: MIT
Platform: UNKNOWN
Requires-Python: >=3.6
